masta_tools/__init__.py
masta_tools/collection.py
masta_tools/converters.py
masta_tools/file.py
masta_tools/key_gen.py
masta_tools/point.py
masta_tools/temp_file.py
masta_tools-0.1.2.dist-info/METADATA
masta_tools-0.1.2.dist-info/WHEEL
masta_tools-0.1.2.dist-info/top_level.txt
masta_tools-0.1.2.dist-info/RECORD
