Metadata-Version: 2.2
Name: masta-tools
Version: 0.1.2
Summary: A suite of useful tools.
Author-email: Matt Owen <matt@dealerclear.com>
License: MIT
Project-URL: Homepage, https://github.com/mastamatto/masta_tools
Project-URL: Repository, https://github.com/mastamatto/masta_tools
Project-URL: Issues, https://github.com/mastamatto/masta_tools/issues
Classifier: Development Status :: 3 - Alpha
Classifier: Intended Audience :: Developers
Classifier: Topic :: Software Development :: Libraries :: Python Modules
Classifier: License :: OSI Approved :: MIT License
Classifier: Programming Language :: Python :: 3
Classifier: Programming Language :: Python :: 3.7
Classifier: Programming Language :: Python :: 3.8
Classifier: Programming Language :: Python :: 3.9
Classifier: Programming Language :: Python :: 3.10
Classifier: Operating System :: OS Independent
Requires-Python: >=3.7
Requires-Dist: pandas
